hosker_utils/__init__.py
hosker_utils/continuous_integration.py
hosker_utils/hm_software_installer.py
hosker_utils/hmss_config.py
hosker_utils/install_dependencies.py
hosker_utils/misc.py
hosker_utils/royal_repos_backup.py
hosker_utils/backup_configs/backup_pylintrc
hosker_utils/backup_configs/backup_pytest.ini
hosker_utils/sh/install_hmss_base.sh
hosker_utils/wallpaper/default.jpg
hosker_utils/wallpaper/wallpaper_t1.png
hosker_utils/wallpaper/wallpaper_t2.png
hosker_utils/wallpaper/wallpaper_t3.png
hosker_utils/wallpaper/wallpaper_t4_(phone).png
hosker_utils/wallpaper/wallpaper_t5.png
hosker_utils/wallpaper/thunderbird_infographics/t1.jpg
hosker_utils/wallpaper/thunderbird_infographics/t2.jpg
hosker_utils/wallpaper/thunderbird_infographics/t3.jpg
hosker_utils/wallpaper/thunderbird_infographics/t4.jpg
hosker_utils/wallpaper/thunderbird_infographics/t5.jpg
hosker_utils-2.6.1.data/scripts/back-up-royal-repos
hosker_utils-2.6.1.data/scripts/install-hmss
hosker_utils-2.6.1.data/scripts/schedule-back-up-royal-repos
hosker_utils-2.6.1.dist-info/LICENSE
hosker_utils-2.6.1.dist-info/METADATA
hosker_utils-2.6.1.dist-info/WHEEL
hosker_utils-2.6.1.dist-info/top_level.txt
hosker_utils-2.6.1.dist-info/RECORD
